MANIFEST.in
README.txt
setup.py
XStatic_Angular_Schema_Form_Bootstrap.egg-info/PKG-INFO
XStatic_Angular_Schema_Form_Bootstrap.egg-info/SOURCES.txt
XStatic_Angular_Schema_Form_Bootstrap.egg-info/dependency_links.txt
XStatic_Angular_Schema_Form_Bootstrap.egg-info/namespace_packages.txt
XStatic_Angular_Schema_Form_Bootstrap.egg-info/not-zip-safe
XStatic_Angular_Schema_Form_Bootstrap.egg-info/top_level.txt
xstatic/__init__.py
xstatic/pkg/__init__.py
xstatic/pkg/angular_schema_form_bootstrap/__init__.py
xstatic/pkg/angular_schema_form_bootstrap/data/bootstrap-decorator.js
xstatic/pkg/angular_schema_form_bootstrap/data/bootstrap-decorator.min.js