Metadata-Version: 1.0
Name: XStatic-Angular-Schema-Form-Bootstrap
Version: 0.2.0.0
Summary: Angular-Schema-Form-Bootstrap 0.2.0 (XStatic packaging standard)
Home-page: http://schemaform.io/
Author: Rob Cresswell
Author-email: robert.cresswell@outlook.com
License: MIT
Keywords: angular_schema_form_bootstrap xstatic
Platform: any
